ssoready/__init__.py
ssoready/client.py
ssoready/core/__init__.py
ssoready/core/api_error.py
ssoready/core/client_wrapper.py
ssoready/core/datetime_utils.py
ssoready/core/file.py
ssoready/core/http_client.py
ssoready/core/jsonable_encoder.py
ssoready/core/pydantic_utilities.py
ssoready/core/query_encoder.py
ssoready/core/remove_none_from_dict.py
ssoready/core/request_options.py
ssoready/environment.py
ssoready/py.typed
ssoready/saml/__init__.py
ssoready/saml/client.py
ssoready/scim/__init__.py
ssoready/scim/client.py
ssoready/types/__init__.py
ssoready/types/get_saml_redirect_url_response.py
ssoready/types/get_scim_group_response.py
ssoready/types/get_scim_user_response.py
ssoready/types/google_protobuf_any.py
ssoready/types/list_scim_groups_response.py
ssoready/types/list_scim_users_response.py
ssoready/types/redeem_saml_access_code_response.py
ssoready/types/scim_group.py
ssoready/types/scim_user.py
ssoready/types/status.py
ssoready/version.py
ssoready-1.0.1.dist-info/LICENSE
ssoready-1.0.1.dist-info/METADATA
ssoready-1.0.1.dist-info/WHEEL
ssoready-1.0.1.dist-info/RECORD
